MANIFEST.in
README.rst
VERSION
setup.cfg
setup.py
redis_drs/__init__.py
redis_drs/main.py
redis_drs/monitor.py
redis_drs.egg-info/PKG-INFO
redis_drs.egg-info/SOURCES.txt
redis_drs.egg-info/dependency_links.txt
redis_drs.egg-info/top_level.txt
test/test_all.py